{
  "Server": {
    "1": {
      "type": "login",
      "port": 6112
    },
    "100": {
      "type": "world",
      "name": "Onyx",
      "host": "127.0.0.1",
      "port": 9875,
      "maxClients": 250
    }
  },
  "Plugins": [{
    "name": "Bot",
    "enabled": true,
    "path": "Plugins/Bot"
  }, {
    "name": "Commands",
    "enabled": true,
    "path": "Plugins/Commands"
  }, {
    "name": "Censor",
    "enabled": true,
    "path": "Plugins/Censor"
  }],
  "Database": {
    "host": "localhost",
    "user": "matheuschimelli",
    "pass": "",
    "database": "c9"
  }
}